sinaasappel/__init__.py
sinaasappel/recursive/__init__.py
sinaasappel/recursive/utils.py
sinaasappel-0.1.19.dist-info/LICENSE
sinaasappel-0.1.19.dist-info/METADATA
sinaasappel-0.1.19.dist-info/WHEEL
sinaasappel-0.1.19.dist-info/RECORD
