Metadata-Version: 2.1
Name: sinaasappel
Version: 0.1.19
Summary: Useful utils
License: Unlicense
Author: nicolasspring
Author-email: springn.ch@gmail.com
Requires-Python: >=3.10,<4.0
Classifier: License :: OSI Approved
Classifier: Programming Language :: Python :: 3
Classifier: Programming Language :: Python :: 3.10
Classifier: Programming Language :: Python :: 3.11
Classifier: Programming Language :: Python :: 3.12
Classifier: Programming Language :: Python :: 3.13
Requires-Dist: numpy (>=2.1.3,<3.0.0)
